analytics_zoo-0.11.2.data/scripts/cluster-serving-cli
analytics_zoo-0.11.2.data/scripts/cluster-serving-init
analytics_zoo-0.11.2.data/scripts/cluster-serving-py-setup.py
analytics_zoo-0.11.2.data/scripts/cluster-serving-restart
analytics_zoo-0.11.2.data/scripts/cluster-serving-shutdown
analytics_zoo-0.11.2.data/scripts/cluster-serving-start
analytics_zoo-0.11.2.data/scripts/cluster-serving-stop
analytics_zoo-0.11.2.data/scripts/cluster-with-numactl.sh
analytics_zoo-0.11.2.data/scripts/config.yaml
analytics_zoo-0.11.2.data/scripts/download-serving-jar.sh
zoo/__init__.py
zoo/automl/__init__.py
zoo/automl/common/__init__.py
zoo/automl/common/metrics.py
zoo/automl/common/parameters.py
zoo/automl/common/util.py
zoo/automl/logger/__init__.py
zoo/automl/logger/tensorboardxlogger.py
zoo/automl/model/__init__.py
zoo/automl/model/abstract.py
zoo/automl/model/base_keras_model.py
zoo/automl/model/base_pytorch_model.py
zoo/automl/pipeline/__init__.py
zoo/automl/pipeline/base.py
zoo/automl/recipe/base.py
zoo/automl/regression/__init__.py
zoo/automl/regression/base_predictor.py
zoo/automl/search/__init__.py
zoo/automl/search/base.py
zoo/automl/search/ray_tune_search_engine.py
zoo/chronos/__init__.py
zoo/chronos/autots/__init__.py
zoo/chronos/autots/forecast.py
zoo/chronos/autots/experimental/__init__.py
zoo/chronos/autots/experimental/autotsestimator.py
zoo/chronos/autots/experimental/tspipeline.py
zoo/chronos/autots/model/__init__.py
zoo/chronos/autots/model/auto_arima.py
zoo/chronos/autots/model/auto_lstm.py
zoo/chronos/autots/model/auto_prophet.py
zoo/chronos/autots/model/auto_tcn.py
zoo/chronos/config/__init__.py
zoo/chronos/config/recipe.py
zoo/chronos/data/__init__.py
zoo/chronos/data/tsdataset.py
zoo/chronos/data/utils/__init__.py
zoo/chronos/data/utils/deduplicate.py
zoo/chronos/data/utils/feature.py
zoo/chronos/data/utils/impute.py
zoo/chronos/data/utils/resample.py
zoo/chronos/data/utils/roll.py
zoo/chronos/data/utils/scale.py
zoo/chronos/data/utils/split.py
analytics_zoo-0.11.2.dist-info/METADATA
analytics_zoo-0.11.2.dist-info/WHEEL
analytics_zoo-0.11.2.dist-info/dependency_links.txt
analytics_zoo-0.11.2.dist-info/top_level.txt
analytics_zoo-0.11.2.dist-info/RECORD
